icemac.ab.importer-2.12-py3.7-nspkg.pth
icemac/ab/importer/__init__.py
icemac/ab/importer/configure.zcml
icemac/ab/importer/conftest.py
icemac/ab/importer/ftesting.zcml
icemac/ab/importer/importer.py
icemac/ab/importer/install.py
icemac/ab/importer/interfaces.py
icemac/ab/importer/source.py
icemac/ab/importer/testing.py
icemac/ab/importer/browser/__init__.py
icemac/ab/importer/browser/configure.zcml
icemac/ab/importer/browser/conftest.py
icemac/ab/importer/browser/file.py
icemac/ab/importer/browser/importer.pt
icemac/ab/importer/browser/importer.py
icemac/ab/importer/browser/menu.py
icemac/ab/importer/browser/readers.pt
icemac/ab/importer/browser/readers.py
icemac/ab/importer/browser/table.py
icemac/ab/importer/browser/tests/__init__.py
icemac/ab/importer/browser/tests/test_importer.py
icemac/ab/importer/browser/tests/test_menu.py
icemac/ab/importer/browser/tests/test_readers.py
icemac/ab/importer/browser/tests/test_table.py
icemac/ab/importer/browser/wizard/__init__.py
icemac/ab/importer/browser/wizard/base.py
icemac/ab/importer/browser/wizard/complete.pt
icemac/ab/importer/browser/wizard/complete.py
icemac/ab/importer/browser/wizard/configure.zcml
icemac/ab/importer/browser/wizard/edit.py
icemac/ab/importer/browser/wizard/map.py
icemac/ab/importer/browser/wizard/reader.py
icemac/ab/importer/browser/wizard/review.pt
icemac/ab/importer/browser/wizard/review.py
icemac/ab/importer/browser/wizard/tests/__init__.py
icemac/ab/importer/browser/wizard/tests/conftest.py
icemac/ab/importer/browser/wizard/tests/test_base.py
icemac/ab/importer/browser/wizard/tests/test_edit.py
icemac/ab/importer/browser/wizard/tests/test_endtoend.py
icemac/ab/importer/browser/wizard/tests/test_map.py
icemac/ab/importer/browser/wizard/tests/test_reader.py
icemac/ab/importer/browser/wizard/tests/test_review.py
icemac/ab/importer/generations/__init__.py
icemac/ab/importer/generations/configure.zcml
icemac/ab/importer/generations/install.py
icemac/ab/importer/reader/__init__.py
icemac.ab.importer-2.12.dist-info/LICENSE.TXT
icemac.ab.importer-2.12.dist-info/METADATA
icemac.ab.importer-2.12.dist-info/WHEEL
icemac.ab.importer-2.12.dist-info/namespace_packages.txt
icemac.ab.importer-2.12.dist-info/top_level.txt
icemac.ab.importer-2.12.dist-info/RECORD
