Metadata-Version: 2.1
Name: icemac.ab.importer
Version: 2.12
Summary: Import infrastructure for icemac.addressbook
Home-page: https://pypi.org/project/icemac.ab.importer
Author: Michael Howitz
Author-email: icemac@gmx.net
License: MIT
Keywords: icemac.addressbook
Platform: UNKNOWN
Classifier: Development Status :: 5 - Production/Stable
Classifier: Environment :: Web Environment
Classifier: Framework :: Zope3
Classifier: License :: OSI Approved :: MIT License
Classifier: Natural Language :: English
Classifier: Natural Language :: German
Classifier: Operating System :: OS Independent
Classifier: Programming Language :: Python :: 2 :: Only
Classifier: Programming Language :: Python :: 2.7
Classifier: Programming Language :: Python :: Implementation :: CPython
Requires-Dist: gocept.cache
Requires-Dist: grokcore.component
Requires-Dist: icemac.ab.locales (>=0.8)
Requires-Dist: icemac.addressbook (>=9.3.dev0)
Requires-Dist: icemac.truncatetext (>=0.2)
Requires-Dist: pytz
Requires-Dist: setuptools
Requires-Dist: z3c.wizard
Requires-Dist: zc.sourcefactory
Requires-Dist: zope.container
Requires-Dist: zope.generations
Requires-Dist: zope.interface
Requires-Dist: zope.schema
Requires-Dist: zope.securitypolicy (>=4.1)
Provides-Extra: test
Requires-Dist: icemac.addressbook[test] ; extra == 'test'
Requires-Dist: zope.testing (>=3.8.0) ; extra == 'test'
Requires-Dist: zope.traversing ; extra == 'test'
